quick_eda/__init__.py
quick_eda/column_eda.py
quick_eda/df_eda.py
quick_eda-0.1.8.dist-info/LICENSE
quick_eda-0.1.8.dist-info/METADATA
quick_eda-0.1.8.dist-info/WHEEL
quick_eda-0.1.8.dist-info/top_level.txt
quick_eda-0.1.8.dist-info/RECORD
