Metadata-Version: 2.1
Name: quick-eda
Version: 0.1.8
Summary: Important dataframe statistics with a single command
Home-page: http://pypi.python.org/pypi/quick_eda/
Author: Sven Eschlbeck
Author-email: sven.eschlbeck@t-online.de
License: LICENSE.txt
Platform: UNKNOWN
License-File: LICENSE
Requires-Dist: pandas
